[{"timestamp":1716621266226,"files":[{"filename":"bundle.*****.esm.js","previous":6556,"size":6576,"diff":20},{"filename":"polyfills.*****.esm.js","previous":2317,"size":2317,"diff":0},{"filename":"sw.js","previous":11382,"size":11382,"diff":0},{"filename":"sw-esm.js","previous":11388,"size":11388,"diff":0},{"filename":"polyfills.a52ec.js","previous":2415,"size":2415,"diff":0},{"filename":"index.html","previous":688,"size":687,"diff":-1},{"filename":"200.html","previous":676,"size":675,"diff":-1},{"filename":"bundle.a3908.css","previous":377,"size":377,"diff":0},{"filename":"bundle.1eced.js","previous":6983,"size":0,"diff":-6983},{"filename":"bundle.a8aff.js","previous":0,"size":7003,"diff":7003}]},{"timestamp":1716620884781,"files":[{"filename":"bundle.*****.esm.js","previous":6541,"size":6556,"diff":15},{"filename":"polyfills.*****.esm.js","previous":2317,"size":2317,"diff":0},{"filename":"sw.js","previous":11382,"size":11382,"diff":0},{"filename":"sw-esm.js","previous":11386,"size":11388,"diff":2},{"filename":"polyfills.a52ec.js","previous":2415,"size":2415,"diff":0},{"filename":"index.html","previous":688,"size":688,"diff":0},{"filename":"200.html","previous":676,"size":676,"diff":0},{"filename":"bundle.a3908.css","previous":377,"size":377,"diff":0},{"filename":"bundle.0fa45.js","previous":6968,"size":0,"diff":-6968},{"filename":"bundle.1eced.js","previous":0,"size":6983,"diff":6983}]},{"timestamp":1716535398078,"files":[{"filename":"bundle.*****.esm.js","previous":6514,"size":6541,"diff":27},{"filename":"polyfills.*****.esm.js","previous":2317,"size":2317,"diff":0},{"filename":"sw.js","previous":11380,"size":11382,"diff":2},{"filename":"sw-esm.js","previous":11385,"size":11386,"diff":1},{"filename":"polyfills.a52ec.js","previous":2415,"size":2415,"diff":0},{"filename":"index.html","previous":689,"size":688,"diff":-1},{"filename":"200.html","previous":676,"size":676,"diff":0},{"filename":"bundle.a3908.css","previous":377,"size":377,"diff":0},{"filename":"bundle.357f1.js","previous":6941,"size":0,"diff":-6941},{"filename":"bundle.0fa45.js","previous":0,"size":6968,"diff":6968}]},{"timestamp":1716533237991,"files":[{"filename":"bundle.*****.esm.js","previous":6208,"size":6514,"diff":306},{"filename":"polyfills.*****.esm.js","previous":2317,"size":2317,"diff":0},{"filename":"sw.js","previous":11382,"size":11380,"diff":-2},{"filename":"sw-esm.js","previous":11387,"size":11385,"diff":-2},{"filename":"polyfills.a52ec.js","previous":2415,"size":2415,"diff":0},{"filename":"index.html","previous":690,"size":689,"diff":-1},{"filename":"200.html","previous":676,"size":676,"diff":0},{"filename":"bundle.a3908.css","previous":377,"size":377,"diff":0},{"filename":"bundle.b31e4.js","previous":6189,"size":0,"diff":-6189},{"filename":"bundle.357f1.js","previous":0,"size":6941,"diff":6941}]},{"timestamp":1716509546197,"files":[{"filename":"bundle.*****.esm.js","previous":7704,"size":6208,"diff":-1496},{"filename":"polyfills.*****.esm.js","previous":2317,"size":2317,"diff":0},{"filename":"sw.js","previous":11382,"size":11382,"diff":0},{"filename":"sw-esm.js","previous":11387,"size":11387,"diff":0},{"filename":"polyfills.a52ec.js","previous":2415,"size":2415,"diff":0},{"filename":"index.html","previous":671,"size":690,"diff":19},{"filename":"200.html","previous":677,"size":676,"diff":-1},{"filename":"bundle.a3908.css","previous":377,"size":377,"diff":0},{"filename":"bundle.f65e9.js","previous":7679,"size":0,"diff":-7679},{"filename":"bundle.b31e4.js","previous":0,"size":6189,"diff":6189}]},{"timestamp":1716508232382,"files":[{"filename":"bundle.dddf4.css","previous":617,"size":0,"diff":-617},{"filename":"bundle.*****.esm.js","previous":9047,"size":7704,"diff":-1343},{"filename":"polyfills.*****.esm.js","previous":2317,"size":2317,"diff":0},{"filename":"route-home.chunk.df06b.css","previous":407,"size":0,"diff":-407},{"filename":"route-home.chunk.*****.esm.js","previous":605,"size":0,"diff":-605},{"filename":"route-profile.chunk.*****.esm.js","previous":1419,"size":0,"diff":-1419},{"filename":"sw.js","previous":11423,"size":11382,"diff":-41},{"filename":"sw-esm.js","previous":11427,"size":11387,"diff":-40},{"filename":"bundle.09736.js","previous":9092,"size":0,"diff":-9092},{"filename":"polyfills.a52ec.js","previous":2415,"size":2415,"diff":0},{"filename":"route-home.chunk.36a5b.js","previous":608,"size":0,"diff":-608},{"filename":"route-profile.chunk.bb625.js","previous":1946,"size":0,"diff":-1946},{"filename":"index.html","previous":1706,"size":671,"diff":-1035},{"filename":"200.html","previous":677,"size":677,"diff":0},{"filename":"bundle.a3908.css","previous":0,"size":377,"diff":377},{"filename":"bundle.f65e9.js","previous":0,"size":7679,"diff":7679}]},{"timestamp":1716506893549,"files":[{"filename":"ssr-build/ssr-bundle.47f9a.css","previous":930,"size":0,"diff":-930},{"filename":"ssr-build/ssr-bundle.js","previous":8749,"size":0,"diff":-8749},{"filename":"bundle.dddf4.css","previous":0,"size":617,"diff":617},{"filename":"bundle.*****.esm.js","previous":0,"size":9047,"diff":9047},{"filename":"polyfills.*****.esm.js","previous":0,"size":2317,"diff":2317},{"filename":"route-home.chunk.df06b.css","previous":0,"size":407,"diff":407},{"filename":"route-home.chunk.*****.esm.js","previous":0,"size":605,"diff":605},{"filename":"route-profile.chunk.*****.esm.js","previous":0,"size":1419,"diff":1419},{"filename":"sw.js","previous":0,"size":11423,"diff":11423},{"filename":"sw-esm.js","previous":0,"size":11427,"diff":11427},{"filename":"bundle.09736.js","previous":0,"size":9092,"diff":9092},{"filename":"polyfills.a52ec.js","previous":0,"size":2415,"diff":2415},{"filename":"route-home.chunk.36a5b.js","previous":0,"size":608,"diff":608},{"filename":"route-profile.chunk.bb625.js","previous":0,"size":1946,"diff":1946},{"filename":"index.html","previous":0,"size":1706,"diff":1706},{"filename":"200.html","previous":0,"size":677,"diff":677}]}]
